footballpitchplot-0.1.dist-info/WHEEL
footballpitchplot-0.1.dist-info/DESCRIPTION.rst
footballpitchplot-0.1.dist-info/top_level.txt
footballpitchplot-0.1.dist-info/METADATA
footballpitchplot-0.1.dist-info/metadata.json
footballpitchplot-0.1.dist-info/RECORD
pitchplotter/plotter.py
pitchplotter/__init__.py
