Metadata-Version: 2.0
Name: footballpitchplot
Version: 0.1
Summary: Python library using Plotly for plotting a football pitch with events.
Home-page: https://github.com/olalidmark/footballpitchplot
Author: fantomen
Author-email: olalidmark@gmail.com
License: MIT
Keywords: football,soccer,metrics,sports,statistics,plotly,plot
Platform: UNKNOWN
Classifier: Development Status :: 4 - Beta
Classifier: Intended Audience :: Developers
Classifier: License :: OSI Approved :: MIT License
Classifier: Programming Language :: Python :: 2
Classifier: Programming Language :: Python :: 2.7
Requires-Dist: plotly
